Workbook
Name ___thinkcellNUYAAAAAAAAAAAAAT8cFbKKya0yTufg8mNIwXQ: #REF!
Name ___thinkcellNUYAAAAAAAAAAAAAT8cFbKKya0yTufg8mNIwXQ: #REF!
Name Dto: #REF!
Name Dto: #REF!
Name Mant_HW_Com: #REF!
Name Mant_HW_Com: #REF!
Name Mante_HW: #REF!
Name Mante_HW: #REF!

Sheet INSTRUCCIONES
B1: SUELDO BRUTO | C1: SUELDO BRUTO C/SAC | D1: CS PV (36,88%) | E1: HS MENSUALES | F1: VALOR HORA | H1: CS | I1: CARGAS SOCIALES
A2: Project Manager | B2: 1500 | C2: 0 | D2: =C2*36.88% -> 0 | E2: 160 | F2: =(B2+C2)/E2 -> 9.375 | H2: PV | I2: PLUS VACACIONAL
A3: Analista Funcional | B3: 1500 | C3: 1 | D3: =C3*36.88% -> 0.3688 | E3: 161 | F3: =(B3+C3)/E3 -> 9.3229814
A4: Sponsor | B4: 1500 | C4: 2 | D4: =C4*36.88% -> 0.7376 | E4: 162 | F4: =(B4+C4)/E4 -> 9.2716049
A5: Institución Piloto | B5: 1500 | C5: 3 | D5: =C5*36.88% -> 1.1064 | E5: 163 | F5: =(B5+C5)/E5 -> 9.2208589
A6: Product Owner | B6: 1500 | C6: 4 | D6: =C6*36.88% -> 1.4752 | E6: 164 | F6: =(B6+C6)/E6 -> 9.1707317
A7: Finanzas | B7: 1500 | C7: 5 | D7: =C7*36.88% -> 1.844 | E7: 165 | F7: =(B7+C7)/E7 -> 9.1212121
A8: Arquitecto de Software | B8: 1500 | C8: 6 | D8: =C8*36.88% -> 2.2128 | E8: 166 | F8: =(B8+C8)/E8 -> 9.0722892
A9: DevOps | B9: 1500 | C9: 7 | D9: =C9*36.88% -> 2.5816 | E9: 167 | F9: =(B9+C9)/E9 -> 9.0239521
A10: Responsable de Seguridad | B10: 1500 | C10: 8 | D10: =C10*36.88% -> 2.9504 | E10: 168 | F10: =(B10+C10)/E10 -> 8.9761905
A11: Arquitecto de Base de Datos | B11: 900 | C11: 0 | D11: =C11*36.88% -> 0 | E11: 160 | F11: =(B11+C11)/E11 -> 5.625
A12: Desarrollador Backend | B12: 600 | C12: 0 | D12: =C12*36.88% -> 0 | E12: 160 | F12: =(B12+C12)/E12 -> 3.75
A13: Desarrollador Frontend | B13: 500 | C13: 0 | D13: =C13*36.88% -> 0 | E13: 160 | F13: =(B13+C13)/E13 -> 3.125
A14: QA Consultant | B14: 500 | C14: 0 | D14: =C14*36.88% -> 0 | E14: 160 | F14: =(B14+C14)/E14 -> 3.125
A15: Soporte | B15: 500 | C15: 0 | D15: =C15*36.88% -> 0 | E15: 160 | F15: =(B15+C15)/E15 -> 3.125
A18: INSTRUCCIONES PARA USAR LA PLANILLA
A20: 1) COMPLETAR EN ESTA HOJA EL NOMBRE, ROL Y SUELDO BRUTO DE CADA INTEGRANTE DEL PROYECTO (EN AMARILLO)
A21: 2) COMPLETAR EN LA HOJA CALCULOS LA CANTIDAD DE HORAS POR CADA INTEGRANTE DEL EQUIPO POR MES. ESTE DATO LO PUEDE CALCULAR AUTOMÁTICAMENTE EL MS PROJECT EN LA HOJA DE RECURSOS, CAMBIANDO LA ESCALA HACIENDO CLICK DERECHO SOBRE LA LINEA DE TIEMPO.
A22: 3) COMPLETAR EL COSTO ASOCIADO A RIESGOS, TAMBIEN MARCADO EN AMARILLO EN LA HOJA DE CALCULOS

Sheet CALCULOS AUXILIARES
A1: AUXILIAR COSTOS
A2: 1) HORAS (Sale de Project) | P2: Porcentaje distrubución de hs sobre total
B3: 46113 | C3: =B3+31 -> 46144 | D3: =C3+31 -> 46175 | E3: =D3+31 -> 46206 | F3: =E3+31 -> 46237 | G3: =F3+31 -> 46268 | H3: =G3+31 -> 46299 | I3: =H3+31 -> 46330 | J3: =I3+31 -> 46361 | ... N3: =M3+31 -> 46485 | P3: Resource Name | Q3: =B3 -> 46113 | R3: =C3 -> 46144 | S3: =D3 -> 46175 | T3: =E3 -> 46206 | U3: =F3 -> 46237 | V3: =G3 -> 46268 | W3: =H3 -> 46299 | X3: =I3 -> 46330 | ... AC3: =N3 -> 46485
A4: =INSTRUCCIONES!A2 -> Project Manager | B4: 28 | C4: 30 | D4: 30 | E4: 30 | F4: 30 | G4: 30 | H4: 30 | I4: 30 | J4: 30 | K4: 30 | L4: 30 | M4: 30 | N4: 30 | P4: =A4 -> Project Manager | Q4: =B4/B$18 -> 0.071428571 | R4: =C4/C$18 -> 0.071428571 | S4: =D4/D$18 -> 0.071428571 | T4: =E4/E$18 -> 0.071428571 | U4: =F4/F$18 -> 0.071428571 | V4: =G4/G$18 -> 0.071428571 | W4: =H4/H$18 -> 0.071428571 | X4: =I4/I$18 -> 0.071428571 | ... AC4: =N4/N$18 -> 0.071428571
A5: =INSTRUCCIONES!A3 -> Analista Funcional | B5: 28 | C5: 30 | D5: 30 | E5: 30 | F5: 30 | G5: 30 | H5: 30 | I5: 30 | J5: 30 | K5: 30 | L5: 30 | M5: 30 | N5: 30 | P5: =A5 -> Analista Funcional
A6: =INSTRUCCIONES!A4 -> Sponsor | B6: 28 | C6: 30 | D6: 30 | E6: 30 | F6: 30 | G6: 30 | H6: 30 | I6: 30 | J6: 30 | K6: 30 | L6: 30 | M6: 30 | N6: 30 | P6: =A6 -> Sponsor
A7: =INSTRUCCIONES!A5 -> Institución Piloto | B7: 28 | C7: 30 | D7: 30 | E7: 30 | F7: 30 | G7: 30 | H7: 30 | I7: 30 | J7: 30 | K7: 30 | L7: 30 | M7: 30 | N7: 30 | P7: =A7 -> Institución Piloto
A8: =INSTRUCCIONES!A6 -> Product Owner | B8: 28 | C8: 30 | D8: 30 | E8: 30 | F8: 30 | G8: 30 | H8: 30 | I8: 30 | J8: 30 | K8: 30 | L8: 30 | M8: 30 | N8: 30 | P8: =A8 -> Product Owner | Q8: =B8/B$18 -> 0.071428571 | R8: =C8/C$18 -> 0.071428571 | S8: =D8/D$18 -> 0.071428571 | T8: =E8/E$18 -> 0.071428571 | U8: =F8/F$18 -> 0.071428571 | V8: =G8/G$18 -> 0.071428571 | W8: =H8/H$18 -> 0.071428571 | X8: =I8/I$18 -> 0.071428571 | ... AC8: =N8/N$18 -> 0.071428571
A9: =INSTRUCCIONES!A7 -> Finanzas | B9: 28 | C9: 30 | D9: 30 | E9: 30 | F9: 30 | G9: 30 | H9: 30 | I9: 30 | J9: 30 | K9: 30 | L9: 30 | M9: 30 | N9: 30 | P9: =A9 -> Finanzas | Q9: =B9/B$18 -> 0.071428571 | R9: =C9/C$18 -> 0.071428571 | S9: =D9/D$18 -> 0.071428571 | T9: =E9/E$18 -> 0.071428571 | U9: =F9/F$18 -> 0.071428571 | V9: =G9/G$18 -> 0.071428571 | W9: =H9/H$18 -> 0.071428571 | X9: =I9/I$18 -> 0.071428571 | ... AC9: =N9/N$18 -> 0.071428571
A10: =INSTRUCCIONES!A8 -> Arquitecto de Software | B10: 28 | C10: 30 | D10: 30 | E10: 30 | F10: 30 | G10: 30 | H10: 30 | I10: 30 | J10: 30 | K10: 30 | L10: 30 | M10: 30 | N10: 30 | P10: =A10 -> Arquitecto de Software
A11: =INSTRUCCIONES!A9 -> DevOps | B11: 28 | C11: 30 | D11: 30 | E11: 30 | F11: 30 | G11: 30 | H11: 30 | I11: 30 | J11: 30 | K11: 30 | L11: 30 | M11: 30 | N11: 30 | P11: =A11 -> DevOps
A12: =INSTRUCCIONES!A10 -> Responsable de Seguridad | B12: 28 | C12: 30 | D12: 30 | E12: 30 | F12: 30 | G12: 30 | H12: 30 | I12: 30 | J12: 30 | K12: 30 | L12: 30 | M12: 30 | N12: 30 | P12: =A12 -> Responsable de Seguridad
A13: =INSTRUCCIONES!A11 -> Arquitecto de Base de Datos | B13: 28 | C13: 30 | D13: 30 | E13: 30 | F13: 30 | G13: 30 | H13: 30 | I13: 30 | J13: 30 | K13: 30 | L13: 30 | M13: 30 | N13: 30 | P13: =A13 -> Arquitecto de Base de Datos
A14: =INSTRUCCIONES!A12 -> Desarrollador Backend | B14: 28 | C14: 30 | D14: 30 | E14: 30 | F14: 30 | G14: 30 | H14: 30 | I14: 30 | J14: 30 | K14: 30 | L14: 30 | M14: 30 | N14: 30 | P14: =A14 -> Desarrollador Backend | Q14: =B14/B$18 -> 0.071428571 | R14: =C14/C$18 -> 0.071428571 | S14: =D14/D$18 -> 0.071428571 | T14: =E14/E$18 -> 0.071428571 | U14: =F14/F$18 -> 0.071428571 | V14: =G14/G$18 -> 0.071428571 | W14: =H14/H$18 -> 0.071428571 | X14: =I14/I$18 -> 0.071428571 | ... AC14: =N14/N$18 -> 0.071428571
A15: =INSTRUCCIONES!A13 -> Desarrollador Frontend | B15: 28 | C15: 30 | D15: 30 | E15: 30 | F15: 30 | G15: 30 | H15: 30 | I15: 30 | J15: 30 | K15: 30 | L15: 30 | M15: 30 | N15: 30 | P15: =A15 -> Desarrollador Frontend | Q15: =B15/B$18 -> 0.071428571 | R15: =C15/C$18 -> 0.071428571 | S15: =D15/D$18 -> 0.071428571 | T15: =E15/E$18 -> 0.071428571 | U15: =F15/F$18 -> 0.071428571 | V15: =G15/G$18 -> 0.071428571 | W15: =H15/H$18 -> 0.071428571 | X15: =I15/I$18 -> 0.071428571 | ... AC15: =N15/N$18 -> 0.071428571
A16: =INSTRUCCIONES!A14 -> QA Consultant | B16: 28 | C16: 30 | D16: 30 | E16: 30 | F16: 30 | G16: 30 | H16: 30 | I16: 30 | J16: 30 | K16: 30 | L16: 30 | M16: 30 | N16: 30 | P16: =A16 -> QA Consultant | Q16: =B16/B$18 -> 0.071428571 | R16: =C16/C$18 -> 0.071428571 | S16: =D16/D$18 -> 0.071428571 | T16: =E16/E$18 -> 0.071428571 | U16: =F16/F$18 -> 0.071428571 | V16: =G16/G$18 -> 0.071428571 | W16: =H16/H$18 -> 0.071428571 | X16: =I16/I$18 -> 0.071428571 | ... AC16: =N16/N$18 -> 0.071428571
A17: =INSTRUCCIONES!A15 -> Soporte | B17: 28 | C17: 30 | D17: 30 | E17: 30 | F17: 30 | G17: 30 | H17: 30 | I17: 30 | J17: 30 | K17: 30 | L17: 30 | M17: 30 | N17: 30 | P17: =A17 -> Soporte | Q17: =B17/B$18 -> 0.071428571 | R17: =C17/C$18 -> 0.071428571 | S17: =D17/D$18 -> 0.071428571 | T17: =E17/E$18 -> 0.071428571 | U17: =F17/F$18 -> 0.071428571 | V17: =G17/G$18 -> 0.071428571 | W17: =H17/H$18 -> 0.071428571 | X17: =I17/I$18 -> 0.071428571 | ... AC17: =N17/N$18 -> 0.071428571
A18: TOTAL | B18: =SUM(B4:B17) -> 392 | C18: =SUM(C4:C17) -> 420 | D18: =SUM(D4:D17) -> 420 | E18: =SUM(E4:E17) -> 420 | F18: =SUM(F4:F17) -> 420 | G18: =SUM(G4:G17) -> 420 | H18: =SUM(H4:H17) -> 420 | I18: =SUM(I4:I17) -> 420 | ... N18: =SUM(N4:N17) -> 420 | P18: Total | Q18: =B18/SUM($B18:$N18) -> 0.072164948 | R18: =C18/SUM($B18:$N18) -> 0.077319588 | S18: =D18/SUM($B18:$N18) -> 0.077319588 | T18: =E18/SUM($B18:$N18) -> 0.077319588 | U18: =F18/SUM($B18:$N18) -> 0.077319588 | V18: =G18/SUM($B18:$N18) -> 0.077319588 | W18: =H18/SUM($B18:$N18) -> 0.077319588 | X18: =I18/SUM($B18:$N18) -> 0.077319588 | ... AC18: =N18/SUM($B18:$N18) -> 0.077319588
A20: COSTO (PELDAÑO 1)
A21: Resource Name | B21: =B3 -> 46113 | C21: =C3 -> 46144 | D21: =D3 -> 46175 | E21: =E3 -> 46206 | F21: =F3 -> 46237 | G21: =G3 -> 46268 | H21: =H3 -> 46299 | I21: =I3 -> 46330 | ... N21: =N3 -> 46485
A22: =A4 -> Project Manager | B22: =B4*INSTRUCCIONES!$F2 -> 262.5 | C22: =C4*INSTRUCCIONES!$F2 -> 281.25 | D22: =D4*INSTRUCCIONES!$F2 -> 281.25 | E22: =E4*INSTRUCCIONES!$F2 -> 281.25 | F22: =F4*INSTRUCCIONES!$F2 -> 281.25 | G22: =G4*INSTRUCCIONES!$F2 -> 281.25 | H22: =H4*INSTRUCCIONES!$F2 -> 281.25 | I22: =I4*INSTRUCCIONES!$F2 -> 281.25 | ... N22: =N4*INSTRUCCIONES!$F2 -> 281.25
A23: =A5 -> Analista Funcional | B23: =B5*INSTRUCCIONES!$F3 -> 261.04348 | C23: =C5*INSTRUCCIONES!$F3 -> 279.68944 | D23: =D5*INSTRUCCIONES!$F3 -> 279.68944 | E23: =E5*INSTRUCCIONES!$F3 -> 279.68944 | F23: =F5*INSTRUCCIONES!$F3 -> 279.68944 | G23: =G5*INSTRUCCIONES!$F3 -> 279.68944 | H23: =H5*INSTRUCCIONES!$F3 -> 279.68944 | I23: =I5*INSTRUCCIONES!$F3 -> 279.68944 | ... N23: =N5*INSTRUCCIONES!$F3 -> 279.68944
A24: =A6 -> Sponsor | B24: =B6*INSTRUCCIONES!$F4 -> 259.60494 | C24: =C6*INSTRUCCIONES!$F4 -> 278.14815 | D24: =D6*INSTRUCCIONES!$F4 -> 278.14815 | E24: =E6*INSTRUCCIONES!$F4 -> 278.14815 | F24: =F6*INSTRUCCIONES!$F4 -> 278.14815 | G24: =G6*INSTRUCCIONES!$F4 -> 278.14815 | H24: =H6*INSTRUCCIONES!$F4 -> 278.14815 | I24: =I6*INSTRUCCIONES!$F4 -> 278.14815 | ... N24: =N6*INSTRUCCIONES!$F4 -> 278.14815
A25: =A7 -> Institución Piloto | B25: =B7*INSTRUCCIONES!$F5 -> 258.18405 | C25: =C7*INSTRUCCIONES!$F5 -> 276.62577 | D25: =D7*INSTRUCCIONES!$F5 -> 276.62577 | E25: =E7*INSTRUCCIONES!$F5 -> 276.62577 | F25: =F7*INSTRUCCIONES!$F5 -> 276.62577 | G25: =G7*INSTRUCCIONES!$F5 -> 276.62577 | H25: =H7*INSTRUCCIONES!$F5 -> 276.62577 | I25: =I7*INSTRUCCIONES!$F5 -> 276.62577 | ... N25: =N7*INSTRUCCIONES!$F5 -> 276.62577
A26: =A8 -> Product Owner | B26: =B8*INSTRUCCIONES!$F6 -> 256.78049 | C26: =C8*INSTRUCCIONES!$F6 -> 275.12195 | D26: =D8*INSTRUCCIONES!$F6 -> 275.12195 | E26: =E8*INSTRUCCIONES!$F6 -> 275.12195 | F26: =F8*INSTRUCCIONES!$F6 -> 275.12195 | G26: =G8*INSTRUCCIONES!$F6 -> 275.12195 | H26: =H8*INSTRUCCIONES!$F6 -> 275.12195 | I26: =I8*INSTRUCCIONES!$F6 -> 275.12195 | ... N26: =N8*INSTRUCCIONES!$F6 -> 275.12195
A27: =A9 -> Finanzas | B27: =B9*INSTRUCCIONES!$F7 -> 255.39394 | C27: =C9*INSTRUCCIONES!$F7 -> 273.63636 | D27: =D9*INSTRUCCIONES!$F7 -> 273.63636 | E27: =E9*INSTRUCCIONES!$F7 -> 273.63636 | F27: =F9*INSTRUCCIONES!$F7 -> 273.63636 | G27: =G9*INSTRUCCIONES!$F7 -> 273.63636 | H27: =H9*INSTRUCCIONES!$F7 -> 273.63636 | I27: =I9*INSTRUCCIONES!$F7 -> 273.63636 | ... N27: =N9*INSTRUCCIONES!$F7 -> 273.63636
A28: =A10 -> Arquitecto de Software | B28: =B10*INSTRUCCIONES!$F8 -> 254.0241 | C28: =C10*INSTRUCCIONES!$F8 -> 272.16867 | D28: =D10*INSTRUCCIONES!$F8 -> 272.16867 | E28: =E10*INSTRUCCIONES!$F8 -> 272.16867 | F28: =F10*INSTRUCCIONES!$F8 -> 272.16867 | G28: =G10*INSTRUCCIONES!$F8 -> 272.16867 | H28: =H10*INSTRUCCIONES!$F8 -> 272.16867 | I28: =I10*INSTRUCCIONES!$F8 -> 272.16867 | ... N28: =N10*INSTRUCCIONES!$F8 -> 272.16867
A29: =A11 -> DevOps | B29: =B11*INSTRUCCIONES!$F9 -> 252.67066 | C29: =C11*INSTRUCCIONES!$F9 -> 270.71856 | D29: =D11*INSTRUCCIONES!$F9 -> 270.71856 | E29: =E11*INSTRUCCIONES!$F9 -> 270.71856 | F29: =F11*INSTRUCCIONES!$F9 -> 270.71856 | G29: =G11*INSTRUCCIONES!$F9 -> 270.71856 | H29: =H11*INSTRUCCIONES!$F9 -> 270.71856 | I29: =I11*INSTRUCCIONES!$F9 -> 270.71856 | ... N29: =N11*INSTRUCCIONES!$F9 -> 270.71856
A30: =A12 -> Responsable de Seguridad | B30: =B12*INSTRUCCIONES!$F10 -> 251.33333 | C30: =C12*INSTRUCCIONES!$F10 -> 269.28571 | D30: =D12*INSTRUCCIONES!$F10 -> 269.28571 | E30: =E12*INSTRUCCIONES!$F10 -> 269.28571 | F30: =F12*INSTRUCCIONES!$F10 -> 269.28571 | G30: =G12*INSTRUCCIONES!$F10 -> 269.28571 | H30: =H12*INSTRUCCIONES!$F10 -> 269.28571 | I30: =I12*INSTRUCCIONES!$F10 -> 269.28571 | ... N30: =N12*INSTRUCCIONES!$F10 -> 269.28571
A31: =A13 -> Arquitecto de Base de Datos | B31: =B13*INSTRUCCIONES!$F11 -> 157.5 | C31: =C13*INSTRUCCIONES!$F11 -> 168.75 | D31: =D13*INSTRUCCIONES!$F11 -> 168.75 | E31: =E13*INSTRUCCIONES!$F11 -> 168.75 | F31: =F13*INSTRUCCIONES!$F11 -> 168.75 | G31: =G13*INSTRUCCIONES!$F11 -> 168.75 | H31: =H13*INSTRUCCIONES!$F11 -> 168.75 | I31: =I13*INSTRUCCIONES!$F11 -> 168.75 | ... N31: =N13*INSTRUCCIONES!$F11 -> 168.75
A32: =A14 -> Desarrollador Backend | B32: =B14*INSTRUCCIONES!$F12 -> 105 | C32: =C14*INSTRUCCIONES!$F12 -> 112.5 | D32: =D14*INSTRUCCIONES!$F12 -> 112.5 | E32: =E14*INSTRUCCIONES!$F12 -> 112.5 | F32: =F14*INSTRUCCIONES!$F12 -> 112.5 | G32: =G14*INSTRUCCIONES!$F12 -> 112.5 | H32: =H14*INSTRUCCIONES!$F12 -> 112.5 | I32: =I14*INSTRUCCIONES!$F12 -> 112.5 | ... N32: =N14*INSTRUCCIONES!$F12 -> 112.5
A33: =A15 -> Desarrollador Frontend | B33: =B15*INSTRUCCIONES!$F13 -> 87.5 | C33: =C15*INSTRUCCIONES!$F13 -> 93.75 | D33: =D15*INSTRUCCIONES!$F13 -> 93.75 | E33: =E15*INSTRUCCIONES!$F13 -> 93.75 | F33: =F15*INSTRUCCIONES!$F13 -> 93.75 | G33: =G15*INSTRUCCIONES!$F13 -> 93.75 | H33: =H15*INSTRUCCIONES!$F13 -> 93.75 | I33: =I15*INSTRUCCIONES!$F13 -> 93.75 | ... N33: =N15*INSTRUCCIONES!$F13 -> 93.75
A34: =A16 -> QA Consultant | B34: =B16*INSTRUCCIONES!$F14 -> 87.5 | C34: =C16*INSTRUCCIONES!$F14 -> 93.75 | D34: =D16*INSTRUCCIONES!$F14 -> 93.75 | E34: =E16*INSTRUCCIONES!$F14 -> 93.75 | F34: =F16*INSTRUCCIONES!$F14 -> 93.75 | G34: =G16*INSTRUCCIONES!$F14 -> 93.75 | H34: =H16*INSTRUCCIONES!$F14 -> 93.75 | I34: =I16*INSTRUCCIONES!$F14 -> 93.75 | ... N34: =N16*INSTRUCCIONES!$F14 -> 93.75 | P34: Prorrateo P2 Gestion por rol y mes
A35: =A17 -> Soporte | B35: =B17*INSTRUCCIONES!$F15 -> 87.5 | C35: =C17*INSTRUCCIONES!$F15 -> 93.75 | D35: =D17*INSTRUCCIONES!$F15 -> 93.75 | E35: =E17*INSTRUCCIONES!$F15 -> 93.75 | F35: =F17*INSTRUCCIONES!$F15 -> 93.75 | G35: =G17*INSTRUCCIONES!$F15 -> 93.75 | H35: =H17*INSTRUCCIONES!$F15 -> 93.75 | I35: =I17*INSTRUCCIONES!$F15 -> 93.75 | ... N35: =N17*INSTRUCCIONES!$F15 -> 93.75 | P35: Resource Name | Q35: =Q3 -> 46113 | R35: =R3 -> 46144 | S35: =S3 -> 46175 | T35: =T3 -> 46206 | U35: =U3 -> 46237 | V35: =V3 -> 46268 | W35: =W3 -> 46299 | X35: =X3 -> 46330 | ... AC35: =AC3 -> 46485
A36: TOTAL Peldaño 1 | B36: =SUM(B22:B35) -> 2836.535 | C36: =SUM(C22:C35) -> 3039.1446 | D36: =SUM(D22:D35) -> 3039.1446 | E36: =SUM(E22:E35) -> 3039.1446 | F36: =SUM(F22:F35) -> 3039.1446 | G36: =SUM(G22:G35) -> 3039.1446 | H36: =SUM(H22:H35) -> 3039.1446 | I36: =SUM(I22:I35) -> 3039.1446 | ... N36: =SUM(N22:N35) -> 3039.1446 | P36: =A22 -> Project Manager | Q36: =Q4*B$41 -> 105 | R36: =R4*C$41 -> 112.5 | S36: =S4*D$41 -> 112.5 | T36: =T4*E$41 -> 112.5 | U36: =U4*F$41 -> 112.5 | V36: =V4*G$41 -> 112.5 | W36: =W4*H$41 -> 112.5 | X36: =X4*I$41 -> 112.5 | ... AC36: =AC4*N$41 -> 112.5
P37: =A23 -> Analista Funcional | Q37: =Q5*B$41 -> 0 | R37: =R5*C$41 -> 0 | S37: =S5*D$41 -> 0 | T37: =T5*E$41 -> 0 | U37: =U5*F$41 -> 0 | V37: =V5*G$41 -> 0 | W37: =W5*H$41 -> 0 | X37: =X5*I$41 -> 0 | ... AC37: =AC5*N$41 -> 0
A38: 2) PELDAÑO GESTIÓN | P38: =A24 -> Sponsor | Q38: =Q6*B$41 -> 0 | R38: =R6*C$41 -> 0 | S38: =S6*D$41 -> 0 | T38: =T6*E$41 -> 0 | U38: =U6*F$41 -> 0 | V38: =V6*G$41 -> 0 | W38: =W6*H$41 -> 0 | X38: =X6*I$41 -> 0 | ... AC38: =AC6*N$41 -> 0
B39: =B21 -> 46113 | C39: =C21 -> 46144 | D39: =D21 -> 46175 | E39: =E21 -> 46206 | F39: =F21 -> 46237 | G39: =G21 -> 46268 | H39: =H21 -> 46299 | I39: =I21 -> 46330 | ... N39: =N21 -> 46485 | P39: =A25 -> Institución Piloto | Q39: =Q7*B$41 -> 0 | R39: =R7*C$41 -> 0 | S39: =S7*D$41 -> 0 | T39: =T7*E$41 -> 0 | U39: =U7*F$41 -> 0 | V39: =V7*G$41 -> 0 | W39: =W7*H$41 -> 0 | X39: =X7*I$41 -> 0 | ... AC39: =AC7*N$41 -> 0
A40: Horas Peldaño 2 Gestión | B40: =B18*40% -> 156.8 | C40: =C18*40% -> 168 | D40: =D18*40% -> 168 | E40: =E18*40% -> 168 | F40: =F18*40% -> 168 | G40: =G18*40% -> 168 | H40: =H18*40% -> 168 | I40: =I18*40% -> 168 | ... N40: =N18*40% -> 168 | P40: =A26 -> Product Owner | Q40: =Q8*B$41 -> 105 | R40: =R8*C$41 -> 112.5 | S40: =S8*D$41 -> 112.5 | T40: =T8*E$41 -> 112.5 | U40: =U8*F$41 -> 112.5 | V40: =V8*G$41 -> 112.5 | W40: =W8*H$41 -> 112.5 | X40: =X8*I$41 -> 112.5 | ... AC40: =AC8*N$41 -> 112.5
A41: Peldaño 2 Gestión | B41: =B40*INSTRUCCIONES!$F$2 -> 1470 | C41: =C40*INSTRUCCIONES!$F$2 -> 1575 | D41: =D40*INSTRUCCIONES!$F$2 -> 1575 | E41: =E40*INSTRUCCIONES!$F$2 -> 1575 | F41: =F40*INSTRUCCIONES!$F$2 -> 1575 | G41: =G40*INSTRUCCIONES!$F$2 -> 1575 | H41: =H40*INSTRUCCIONES!$F$2 -> 1575 | I41: =I40*INSTRUCCIONES!$F$2 -> 1575 | ... N41: =N40*INSTRUCCIONES!$F$2 -> 1575 | P41: =A27 -> Finanzas | Q41: =Q9*B$41 -> 105 | R41: =R9*C$41 -> 112.5 | S41: =S9*D$41 -> 112.5 | T41: =T9*E$41 -> 112.5 | U41: =U9*F$41 -> 112.5 | V41: =V9*G$41 -> 112.5 | W41: =W9*H$41 -> 112.5 | X41: =X9*I$41 -> 112.5 | ... AC41: =AC9*N$41 -> 112.5
P42: =A28 -> Arquitecto de Software | Q42: =Q10*B$41 -> 0 | R42: =R10*C$41 -> 0 | S42: =S10*D$41 -> 0 | T42: =T10*E$41 -> 0 | U42: =U10*F$41 -> 0 | V42: =V10*G$41 -> 0 | W42: =W10*H$41 -> 0 | X42: =X10*I$41 -> 0 | ... AC42: =AC10*N$41 -> 0
P43: =A29 -> DevOps | Q43: =Q11*B$41 -> 0 | R43: =R11*C$41 -> 0 | S43: =S11*D$41 -> 0 | T43: =T11*E$41 -> 0 | U43: =U11*F$41 -> 0 | V43: =V11*G$41 -> 0 | W43: =W11*H$41 -> 0 | X43: =X11*I$41 -> 0 | ... AC43: =AC11*N$41 -> 0
P44: =A30 -> Responsable de Seguridad | Q44: =Q12*B$41 -> 0 | R44: =R12*C$41 -> 0 | S44: =S12*D$41 -> 0 | T44: =T12*E$41 -> 0 | U44: =U12*F$41 -> 0 | V44: =V12*G$41 -> 0 | W44: =W12*H$41 -> 0 | X44: =X12*I$41 -> 0 | ... AC44: =AC12*N$41 -> 0
P45: =A31 -> Arquitecto de Base de Datos | Q45: =Q13*B$41 -> 0 | R45: =R13*C$41 -> 0 | S45: =S13*D$41 -> 0 | T45: =T13*E$41 -> 0 | U45: =U13*F$41 -> 0 | V45: =V13*G$41 -> 0 | W45: =W13*H$41 -> 0 | X45: =X13*I$41 -> 0 | ... AC45: =AC13*N$41 -> 0
P46: =A32 -> Desarrollador Backend | Q46: =Q14*B$41 -> 105 | R46: =R14*C$41 -> 112.5 | S46: =S14*D$41 -> 112.5 | T46: =T14*E$41 -> 112.5 | U46: =U14*F$41 -> 112.5 | V46: =V14*G$41 -> 112.5 | W46: =W14*H$41 -> 112.5 | X46: =X14*I$41 -> 112.5 | ... AC46: =AC14*N$41 -> 112.5
P47: =A33 -> Desarrollador Frontend | Q47: =Q15*B$41 -> 105 | R47: =R15*C$41 -> 112.5 | S47: =S15*D$41 -> 112.5 | T47: =T15*E$41 -> 112.5 | U47: =U15*F$41 -> 112.5 | V47: =V15*G$41 -> 112.5 | W47: =W15*H$41 -> 112.5 | X47: =X15*I$41 -> 112.5 | ... AC47: =AC15*N$41 -> 112.5
A48: 3) PELDAÑO 3 RESERVA CONTINGENCIA | P48: =A34 -> QA Consultant | Q48: =Q16*B$41 -> 105 | R48: =R16*C$41 -> 112.5 | S48: =S16*D$41 -> 112.5 | T48: =T16*E$41 -> 112.5 | U48: =U16*F$41 -> 112.5 | V48: =V16*G$41 -> 112.5 | W48: =W16*H$41 -> 112.5 | X48: =X16*I$41 -> 112.5 | ... AC48: =AC16*N$41 -> 112.5
B49: =B39 -> 46113 | C49: =C39 -> 46144 | D49: =D39 -> 46175 | E49: =E39 -> 46206 | F49: =F39 -> 46237 | G49: =G39 -> 46268 | H49: =H39 -> 46299 | I49: =I39 -> 46330 | ... N49: =N39 -> 46485 | P49: =A35 -> Soporte | Q49: =Q17*B$41 -> 105 | R49: =R17*C$41 -> 112.5 | S49: =S17*D$41 -> 112.5 | T49: =T17*E$41 -> 112.5 | U49: =U17*F$41 -> 112.5 | V49: =V17*G$41 -> 112.5 | W49: =W17*H$41 -> 112.5 | X49: =X17*I$41 -> 112.5 | ... AC49: =AC17*N$41 -> 112.5
A50: Peldaño 3 Reserva Contingencia
A52: 4) PELDAÑO 4 RESERVA ADMINISTRATIVA | P52: Prorrateo P4 Gestion por rol y mes
B53: =B49 -> 46113 | C53: =C49 -> 46144 | D53: =D49 -> 46175 | E53: =E49 -> 46206 | F53: =F49 -> 46237 | G53: =G49 -> 46268 | H53: =H49 -> 46299 | I53: =I49 -> 46330 | ... N53: =N49 -> 46485 | P53: Resource Name | Q53: =Q35 -> 46113 | R53: =R35 -> 46144 | S53: =Z35 -> 46392 | T53: =AA35 -> 46423 | U53: =AB35 -> 46454 | V53: =AC35 -> 46485
A54: Peldaño 4 Reserva Adm. 40% | B54: =(B41+B36)*40% -> 1722.614 | C54: =(C41+C36)*40% -> 1845.6578 | D54: =(D41+D36)*40% -> 1845.6578 | E54: =(E41+E36)*40% -> 1845.6578 | F54: =(F41+F36)*40% -> 1845.6578 | G54: =(G41+G36)*40% -> 1845.6578 | H54: =(H41+H36)*40% -> 1845.6578 | I54: =(I41+I36)*40% -> 1845.6578 | ... N54: =(N41+N36)*40% -> 1845.6578 | P54: =P36 -> Project Manager | Q54: =Q4*B$54 -> 123.04386 | R54: =R4*C$54 -> 131.8327 | S54: =W4*K$54 -> 131.8327 | T54: =Z4*L$54 -> 131.8327 | U54: =AB4*M$54 -> 131.8327 | V54: =AC4*N$54 -> 131.8327
P55: =P37 -> Analista Funcional | Q55: =Q5*B$54 -> 0 | R55: =R5*C$54 -> 0 | S55: =W5*K$54 -> 0 | T55: =Z5*L$54 -> 0 | U55: =AB5*M$54 -> 0 | V55: =AC5*N$54 -> 0
P56: =P38 -> Sponsor | Q56: =Q6*B$54 -> 0 | R56: =R6*C$54 -> 0 | S56: =W6*K$54 -> 0 | T56: =Z6*L$54 -> 0 | U56: =AB6*M$54 -> 0 | V56: =AC6*N$54 -> 0
P57: =P39 -> Institución Piloto | Q57: =Q7*B$54 -> 0 | R57: =R7*C$54 -> 0 | S57: =W7*K$54 -> 0 | T57: =Z7*L$54 -> 0 | U57: =AB7*M$54 -> 0 | V57: =AC7*N$54 -> 0
P58: =P40 -> Product Owner | Q58: =Q8*B$54 -> 123.04386 | R58: =R8*C$54 -> 131.8327 | S58: =W8*K$54 -> 131.8327 | T58: =Z8*L$54 -> 131.8327 | U58: =AB8*M$54 -> 131.8327 | V58: =AC8*N$54 -> 131.8327
P59: =P41 -> Finanzas | Q59: =Q9*B$54 -> 123.04386 | R59: =R9*C$54 -> 131.8327 | S59: =W9*K$54 -> 131.8327 | T59: =Z9*L$54 -> 131.8327 | U59: =AB9*M$54 -> 131.8327 | V59: =AC9*N$54 -> 131.8327
P60: =P42 -> Arquitecto de Software | Q60: =Q10*B$54 -> 0 | R60: =R10*C$54 -> 0 | S60: =W10*K$54 -> 0 | T60: =Z10*L$54 -> 0 | U60: =AB10*M$54 -> 0 | V60: =AC10*N$54 -> 0
P61: =P43 -> DevOps | Q61: =Q11*B$54 -> 0 | R61: =R11*C$54 -> 0 | S61: =W11*K$54 -> 0 | T61: =Z11*L$54 -> 0 | U61: =AB11*M$54 -> 0 | V61: =AC11*N$54 -> 0
A62: 5) PELDAÑO 5 GANANCIA | P62: =P44 -> Responsable de Seguridad | Q62: =Q12*B$54 -> 0 | R62: =R12*C$54 -> 0 | S62: =W12*K$54 -> 0 | T62: =Z12*L$54 -> 0 | U62: =AB12*M$54 -> 0 | V62: =AC12*N$54 -> 0
B63: =B53 -> 46113 | C63: =C53 -> 46144 | D63: =D53 -> 46175 | E63: =E53 -> 46206 | F63: =F53 -> 46237 | G63: =G53 -> 46268 | H63: =H53 -> 46299 | I63: =I53 -> 46330 | ... N63: =N53 -> 46485 | P63: =P45 -> Arquitecto de Base de Datos | Q63: =Q13*B$54 -> 0 | R63: =R13*C$54 -> 0 | S63: =W13*K$54 -> 0 | T63: =Z13*L$54 -> 0 | U63: =AB13*M$54 -> 0 | V63: =AC13*N$54 -> 0
A64: Peldaño 5 Ganancia 35% | B64: =(B54+B41+B36)*35% -> 2110.2021 | C64: =(C54+C41+C36)*35% -> 2260.9309 | D64: =(D54+D41+D36)*35% -> 2260.9309 | E64: =(E54+E41+E36)*35% -> 2260.9309 | F64: =(F54+F41+F36)*35% -> 2260.9309 | G64: =(G54+G41+G36)*35% -> 2260.9309 | H64: =(H54+H41+H36)*35% -> 2260.9309 | I64: =(I54+I41+I36)*35% -> 2260.9309 | ... N64: =(N54+N41+N36)*35% -> 2260.9309 | P64: =P46 -> Desarrollador Backend | Q64: =Q14*B$54 -> 123.04386 | R64: =R14*C$54 -> 131.8327 | S64: =W14*K$54 -> 131.8327 | T64: =Z14*L$54 -> 131.8327 | U64: =AB14*M$54 -> 131.8327 | V64: =AC14*N$54 -> 131.8327
P65: =P47 -> Desarrollador Frontend | Q65: =Q15*B$54 -> 123.04386 | R65: =R15*C$54 -> 131.8327 | S65: =W15*K$54 -> 131.8327 | T65: =Z15*L$54 -> 131.8327 | U65: =AB15*M$54 -> 131.8327 | V65: =AC15*N$54 -> 131.8327
P66: =P48 -> QA Consultant | Q66: =Q16*B$54 -> 123.04386 | R66: =R16*C$54 -> 131.8327 | S66: =W16*K$54 -> 131.8327 | T66: =Z16*L$54 -> 131.8327 | U66: =AB16*M$54 -> 131.8327 | V66: =AC16*N$54 -> 131.8327
P67: =P49 -> Soporte | Q67: =Q17*B$54 -> 123.04386 | R67: =R17*C$54 -> 131.8327 | S67: =W17*K$54 -> 131.8327 | T67: =Z17*L$54 -> 131.8327 | U67: =AB17*M$54 -> 131.8327 | V67: =AC17*N$54 -> 131.8327
P70: Prorrateo P5 Gestion por rol y mes
P71: Resource Name | Q71: =Q53 -> 46113 | R71: =R53 -> 46144 | S71: =S53 -> 46392 | T71: =T53 -> 46423 | U71: =U53 -> 46454 | V71: =V53 -> 46485
A72: Total x Rol y mes de TODA la pirámide. | P72: =P54 -> Project Manager | Q72: =Q4*B$64 -> 150.72872 | R72: =R4*C$64 -> 161.49506 | S72: =W4*K$64 -> 161.49506 | T72: =Z4*L$64 -> 161.49506 | U72: =AB4*M$64 -> 161.49506 | V72: =AC4*N$64 -> 161.49506
B73: =B63 -> 46113 | C73: =C63 -> 46144 | D73: =D63 -> 46175 | E73: =E63 -> 46206 | F73: =F63 -> 46237 | G73: =G63 -> 46268 | H73: =H63 -> 46299 | I73: =I63 -> 46330 | ... N73: =N63 -> 46485 | P73: =P55 -> Analista Funcional | Q73: =Q5*B$64 -> 0 | R73: =R5*C$64 -> 0 | S73: =W5*K$64 -> 0 | T73: =Z5*L$64 -> 0 | U73: =AB5*M$64 -> 0 | V73: =AC5*N$64 -> 0
A74: =A4 -> Project Manager | B74: =B22+Q36+Q54+Q72 -> 641.27258 | C74: =C22+R36+R54+R72 -> 687.07777 | D74: =D22+S36+S54+S72 -> 687.07777 | E74: =E22+T36+T54+T72 -> 687.07777 | F74: =F22+U36+U54+U72 -> 687.07777 | G74: =G22+V36+V54+V72 -> 687.07777 | H74: =H22+W36+AD54+W72 -> 393.75 | I74: =I22+X36+AE54+X72 -> 393.75 | J74: =J22+Y36+AF54+Y72 -> 393.75 | K74: =K22+Z36+AG54+Z72 -> 393.75 | L74: =L22+AA36+AH54+AA72 -> 393.75 | M74: =M22+AB36+AI54+AB72 -> 393.75 | N74: =N22+AC36+AJ54+AC72 -> 393.75 | P74: =P56 -> Sponsor | Q74: =Q6*B$64 -> 0 | R74: =R6*C$64 -> 0 | S74: =W6*K$64 -> 0 | T74: =Z6*L$64 -> 0 | U74: =AB6*M$64 -> 0 | V74: =AC6*N$64 -> 0
A75: =A5 -> Analista Funcional | B75: =B23+Q37+Q55+Q73 -> 261.04348 | C75: =C23+R37+R55+R73 -> 279.68944 | D75: =D23+S37+S55+S73 -> 279.68944 | E75: =E23+T37+T55+T73 -> 279.68944 | F75: =F23+U37+U55+U73 -> 279.68944 | G75: =G23+V37+V55+V73 -> 279.68944 | H75: =H23+W37+W55+AD73 -> 279.68944 | I75: =I23+X37+X55+AE73 -> 279.68944 | J75: =J23+Y37+Y55+AF73 -> 279.68944 | K75: =K23+Z37+Z55+AG73 -> 279.68944 | L75: =L23+AA37+AA55+AH73 -> 279.68944 | M75: =M23+AB37+AB55+AI73 -> 279.68944 | N75: =N23+AC37+AC55+AJ73 -> 279.68944 | P75: =P57 -> Institución Piloto | Q75: =Q7*B$64 -> 0 | R75: =R7*C$64 -> 0 | S75: =W7*K$64 -> 0 | T75: =Z7*L$64 -> 0 | U75: =AB7*M$64 -> 0 | V75: =AC7*N$64 -> 0
A76: =A6 -> Sponsor | B76: =B24+Q38+Q56+Q74 -> 259.60494 | C76: =C24+R38+R56+R74 -> 278.14815 | D76: =D24+S38+S56+S74 -> 278.14815 | E76: =E24+T38+T56+T74 -> 278.14815 | F76: =F24+U38+U56+U74 -> 278.14815 | G76: =G24+V38+V56+V74 -> 278.14815 | H76: =H24+W38+W56+AD74 -> 278.14815 | I76: =I24+X38+X56+AE74 -> 278.14815 | J76: =J24+Y38+Y56+AF74 -> 278.14815 | K76: =K24+Z38+Z56+AG74 -> 278.14815 | L76: =L24+AA38+AA56+AH74 -> 278.14815 | M76: =M24+AB38+AB56+AI74 -> 278.14815 | N76: =N24+AC38+AC56+AJ74 -> 278.14815 | P76: =P58 -> Product Owner | Q76: =Q8*B$64 -> 150.72872 | R76: =R8*C$64 -> 161.49506 | S76: =W8*K$64 -> 161.49506 | T76: =Z8*L$64 -> 161.49506 | U76: =AB8*M$64 -> 161.49506 | V76: =AC8*N$64 -> 161.49506
A77: =A7 -> Institución Piloto | B77: =B25+Q39+Q57+Q75 -> 258.18405 | C77: =C25+R39+R57+R75 -> 276.62577 | D77: =D25+S39+S57+S75 -> 276.62577 | E77: =E25+T39+T57+T75 -> 276.62577 | F77: =F25+U39+U57+U75 -> 276.62577 | G77: =G25+V39+V57+V75 -> 276.62577 | H77: =H25+W39+W57+AD75 -> 276.62577 | I77: =I25+X39+X57+AE75 -> 276.62577 | J77: =J25+Y39+Y57+AF75 -> 276.62577 | K77: =K25+Z39+Z57+AG75 -> 276.62577 | L77: =L25+AA39+AA57+AH75 -> 276.62577 | M77: =M25+AB39+AB57+AI75 -> 276.62577 | N77: =N25+AC39+AC57+AJ75 -> 276.62577 | P77: =P59 -> Finanzas | Q77: =Q9*B$64 -> 150.72872 | R77: =R9*C$64 -> 161.49506 | S77: =W9*K$64 -> 161.49506 | T77: =Z9*L$64 -> 161.49506 | U77: =AB9*M$64 -> 161.49506 | V77: =AC9*N$64 -> 161.49506
A78: =A8 -> Product Owner | B78: =B26+Q40+Q58+Q76 -> 635.55307 | C78: =C26+R40+R58+R76 -> 680.94972 | D78: =D26+S40+S58+S76 -> 680.94972 | E78: =E26+T40+T58+T76 -> 680.94972 | F78: =F26+U40+U58+U76 -> 680.94972 | G78: =G26+V40+V58+V76 -> 680.94972 | H78: =H26+W40+W58+AD76 -> 387.62195 | I78: =I26+X40+X58+AE76 -> 387.62195 | J78: =J26+Y40+Y58+AF76 -> 387.62195 | K78: =K26+Z40+Z58+AG76 -> 387.62195 | L78: =L26+AA40+AA58+AH76 -> 387.62195 | M78: =M26+AB40+AB58+AI76 -> 387.62195 | N78: =N26+AC40+AC58+AJ76 -> 387.62195 | P78: =P60 -> Arquitecto de Software | Q78: =Q10*B$64 -> 0 | R78: =R10*C$64 -> 0 | S78: =W10*K$64 -> 0 | T78: =Z10*L$64 -> 0 | U78: =AB10*M$64 -> 0 | V78: =AC10*N$64 -> 0
A79: =A9 -> Finanzas | B79: =B27+Q41+Q59+Q77 -> 634.16652 | C79: =C27+R41+R59+R77 -> 679.46413 | D79: =D27+S41+S59+S77 -> 679.46413 | E79: =E27+T41+T59+T77 -> 679.46413 | F79: =F27+U41+U59+U77 -> 679.46413 | G79: =G27+V41+V59+V77 -> 679.46413 | H79: =H27+W41+W59+AD77 -> 386.13636 | I79: =I27+X41+X59+AE77 -> 386.13636 | J79: =J27+Y41+Y59+AF77 -> 386.13636 | K79: =K27+Z41+Z59+AG77 -> 386.13636 | L79: =L27+AA41+AA59+AH77 -> 386.13636 | M79: =M27+AB41+AB59+AI77 -> 386.13636 | N79: =N27+AC41+AC59+AJ77 -> 386.13636 | P79: =P61 -> DevOps | Q79: =Q11*B$64 -> 0 | R79: =R11*C$64 -> 0 | S79: =W11*K$64 -> 0 | T79: =Z11*L$64 -> 0 | U79: =AB11*M$64 -> 0 | V79: =AC11*N$64 -> 0
A80: =A10 -> Arquitecto de Software | B80: =B28+Q42+Q60+Q78 -> 254.0241 | C80: =C28+R42+R60+R78 -> 272.16867 | D80: =D28+S42+S60+S78 -> 272.16867 | E80: =E28+T42+T60+T78 -> 272.16867 | F80: =F28+U42+U60+U78 -> 272.16867 | G80: =G28+V42+V60+V78 -> 272.16867 | H80: =H28+W42+W60+AD78 -> 272.16867 | I80: =I28+X42+X60+AE78 -> 272.16867 | J80: =J28+Y42+Y60+AF78 -> 272.16867 | K80: =K28+Z42+Z60+AG78 -> 272.16867 | L80: =L28+AA42+AA60+AH78 -> 272.16867 | M80: =M28+AB42+AB60+AI78 -> 272.16867 | N80: =N28+AC42+AC60+AJ78 -> 272.16867 | P80: =P62 -> Responsable de Seguridad | Q80: =Q12*B$64 -> 0 | R80: =R12*C$64 -> 0 | S80: =W12*K$64 -> 0 | T80: =Z12*L$64 -> 0 | U80: =AB12*M$64 -> 0 | V80: =AC12*N$64 -> 0
A81: =A11 -> DevOps | B81: =B29+Q43+Q61+Q79 -> 252.67066 | C81: =C29+R43+R61+R79 -> 270.71856 | D81: =D29+S43+S61+S79 -> 270.71856 | E81: =E29+T43+T61+T79 -> 270.71856 | F81: =F29+U43+U61+U79 -> 270.71856 | G81: =G29+V43+V61+V79 -> 270.71856 | H81: =H29+W43+W61+AD79 -> 270.71856 | I81: =I29+X43+X61+AE79 -> 270.71856 | J81: =J29+Y43+Y61+AF79 -> 270.71856 | K81: =K29+Z43+Z61+AG79 -> 270.71856 | L81: =L29+AA43+AA61+AH79 -> 270.71856 | M81: =M29+AB43+AB61+AI79 -> 270.71856 | N81: =N29+AC43+AC61+AJ79 -> 270.71856 | P81: =P63 -> Arquitecto de Base de Datos | Q81: =Q13*B$64 -> 0 | R81: =R13*C$64 -> 0 | S81: =W13*K$64 -> 0 | T81: =Z13*L$64 -> 0 | U81: =AB13*M$64 -> 0 | V81: =AC13*N$64 -> 0
A82: =A12 -> Responsable de Seguridad | B82: =B30+Q44+Q62+Q80 -> 251.33333 | C82: =C30+R44+R62+R80 -> 269.28571 | D82: =D30+S44+S62+S80 -> 269.28571 | E82: =E30+T44+T62+T80 -> 269.28571 | F82: =F30+U44+U62+U80 -> 269.28571 | G82: =G30+V44+V62+V80 -> 269.28571 | H82: =H30+W44+W62+AD80 -> 269.28571 | I82: =I30+X44+X62+AE80 -> 269.28571 | J82: =J30+Y44+Y62+AF80 -> 269.28571 | K82: =K30+Z44+Z62+AG80 -> 269.28571 | L82: =L30+AA44+AA62+AH80 -> 269.28571 | M82: =M30+AB44+AB62+AI80 -> 269.28571 | N82: =N30+AC44+AC62+AJ80 -> 269.28571 | P82: =P64 -> Desarrollador Backend | Q82: =Q14*B$64 -> 150.72872 | R82: =R14*C$64 -> 161.49506 | S82: =W14*K$64 -> 161.49506 | T82: =Z14*L$64 -> 161.49506 | U82: =AB14*M$64 -> 161.49506 | V82: =AC14*N$64 -> 161.49506
A83: =A13 -> Arquitecto de Base de Datos | B83: =B31+Q45+Q63+Q81 -> 157.5 | C83: =C31+R45+R63+R81 -> 168.75 | D83: =D31+S45+S63+S81 -> 168.75 | E83: =E31+T45+T63+T81 -> 168.75 | F83: =F31+U45+U63+U81 -> 168.75 | G83: =G31+V45+V63+V81 -> 168.75 | H83: =H31+W45+AD63+AD81 -> 168.75 | I83: =I31+X45+AE63+AE81 -> 168.75 | J83: =J31+Y45+AF63+AF81 -> 168.75 | K83: =K31+Z45+AG63+AG81 -> 168.75 | L83: =L31+AA45+AH63+AH81 -> 168.75 | M83: =M31+AB45+AI63+AI81 -> 168.75 | N83: =N31+AC45+AJ63+AJ81 -> 168.75 | P83: =P65 -> Desarrollador Frontend | Q83: =Q15*B$64 -> 150.72872 | R83: =R15*C$64 -> 161.49506 | S83: =W15*K$64 -> 161.49506 | T83: =Z15*L$64 -> 161.49506 | U83: =AB15*M$64 -> 161.49506 | V83: =AC15*N$64 -> 161.49506
A84: =A14 -> Desarrollador Backend | B84: =B32+Q46+Q64+Q82 -> 483.77258 | C84: =C32+R46+R64+R82 -> 518.32777 | D84: =D32+S46+S64+S82 -> 518.32777 | E84: =E32+T46+T64+T82 -> 518.32777 | F84: =F32+U46+U64+U82 -> 518.32777 | G84: =G32+V46+V64+V82 -> 518.32777 | H84: =H32+W46+AD64+AD82 -> 225 | I84: =I32+X46+AE64+AE82 -> 225 | J84: =J32+Y46+AF64+AF82 -> 225 | K84: =K32+Z46+AG64+AG82 -> 225 | L84: =L32+AA46+AH64+AH82 -> 225 | M84: =M32+AB46+AI64+AI82 -> 225 | N84: =N32+AC46+AJ64+AJ82 -> 225 | P84: =P66 -> QA Consultant | Q84: =Q16*B$64 -> 150.72872 | R84: =R16*C$64 -> 161.49506 | S84: =W16*K$64 -> 161.49506 | T84: =Z16*L$64 -> 161.49506 | U84: =AB16*M$64 -> 161.49506 | V84: =AC16*N$64 -> 161.49506
A85: =A15 -> Desarrollador Frontend | B85: =B33+Q47+Q65+Q83 -> 466.27258 | C85: =C33+R47+R65+R83 -> 499.57777 | D85: =D33+S47+S65+S83 -> 499.57777 | E85: =E33+T47+T65+T83 -> 499.57777 | F85: =F33+U47+U65+U83 -> 499.57777 | G85: =G33+V47+V65+V83 -> 499.57777 | H85: =H33+W47+W65+AD83 -> 206.25 | I85: =I33+X47+X65+AE83 -> 206.25 | J85: =J33+Y47+Y65+AF83 -> 206.25 | K85: =K33+Z47+Z65+AG83 -> 206.25 | L85: =L33+AA47+AA65+AH83 -> 206.25 | M85: =M33+AB47+AB65+AI83 -> 206.25 | N85: =N33+AC47+AC65+AJ83 -> 206.25 | P85: =P67 -> Soporte | Q85: =Q17*B$64 -> 150.72872 | R85: =R17*C$64 -> 161.49506 | S85: =W17*K$64 -> 161.49506 | T85: =Z17*L$64 -> 161.49506 | U85: =AB17*M$64 -> 161.49506 | V85: =AC17*N$64 -> 161.49506
A86: =A16 -> QA Consultant | B86: =B34+Q48+Q66+Q84 -> 466.27258 | C86: =C34+R48+R66+R84 -> 499.57777 | D86: =D34+S48+S66+S84 -> 499.57777 | E86: =E34+T48+T66+T84 -> 499.57777 | F86: =F34+U48+U66+U84 -> 499.57777 | G86: =G34+V48+V66+V84 -> 499.57777 | H86: =H34+W48+W66+AD84 -> 206.25 | I86: =I34+X48+X66+AE84 -> 206.25 | J86: =J34+Y48+Y66+AF84 -> 206.25 | K86: =K34+Z48+Z66+AG84 -> 206.25 | L86: =L34+AA48+AA66+AH84 -> 206.25 | M86: =M34+AB48+AB66+AI84 -> 206.25 | N86: =N34+AC48+AC66+AJ84 -> 206.25
A87: =A17 -> Soporte | B87: =B35+Q49+Q67+Q85 -> 466.27258 | C87: =C35+R49+R67+R85 -> 499.57777 | D87: =D35+S49+S67+S85 -> 499.57777 | E87: =E35+T49+T67+T85 -> 499.57777 | F87: =F35+U49+U67+U85 -> 499.57777 | G87: =G35+V49+V67+V85 -> 499.57777 | H87: =H35+W49+W67+AD85 -> 206.25 | I87: =I35+X49+X67+AE85 -> 206.25 | J87: =J35+Y49+Y67+AF85 -> 206.25 | K87: =K35+Z49+Z67+AG85 -> 206.25 | L87: =L35+AA49+AA67+AH85 -> 206.25 | M87: =M35+AB49+AB67+AI85 -> 206.25 | N87: =N35+AC49+AC67+AJ85 -> 206.25
A88: Total | B88: =SUM(B74:B87) -> 5487.943 | C88: =SUM(C74:C87) -> 5879.939 | D88: =SUM(D74:D87) -> 5879.939 | E88: =SUM(E74:E87) -> 5879.939 | F88: =SUM(F74:F87) -> 5879.939 | G88: =SUM(G74:G87) -> 5879.939 | H88: =SUM(H74:H87) -> 3826.6446 | I88: =SUM(I74:I87) -> 3826.6446 | ... N88: =SUM(N74:N87) -> 3826.6446
A90: SETUP INICIAL
A91: =A74 -> Project Manager | B91: 50000
A92: =A75 -> Analista Funcional | B92: 50001
A93: =A76 -> Sponsor | B93: 50002
A94: =A77 -> Institución Piloto | B94: 50003
A95: =A78 -> Product Owner | B95: 50004
A96: =A79 -> Finanzas | B96: 50005
A97: =A80 -> Arquitecto de Software | B97: 50006
A98: =A81 -> DevOps | B98: 50007
A99: =A82 -> Responsable de Seguridad | B99: 50008
A100: =A83 -> Arquitecto de Base de Datos | B100: 50009
A101: =A84 -> Desarrollador Backend | B101: 50010
A102: =A85 -> Desarrollador Frontend | B102: 50011
... A104: =A87 -> Soporte | B104: 50013
A105: Total | B105: =SUM(B91:B104) -> 700091
A107: DISTRIBUCIÓN DE COSTOS UNIFORME
...

Sheet Estimación de Costos Básica HR 
A1: Presupuesto de Costos . Calculo de TCO. P&L (Profit & Loss, perdidas y ganancias) Pricing Cloud AWS: https://calculator.s3.amazonaws.com/index.html Princing Cloud Azure: https://azure.microsoft.com/en-us/pricing/calculator/ Pricing Cloud https://cloud.google.com/products/calculator/ Pricing PaaS Heroku: https://www.heroku.com/pricing
A2: Equipo de Proyecto | B2: Meses | O2: Costos Totales por categoría | P2: Consideraciones, y detalles de los costos incluidos en cada partida
A4: Rol / Mes | B4: ='CALCULOS AUXILIARES'!B3 -> 46113 | C4: ='CALCULOS AUXILIARES'!C3 -> 46144 | D4: ='CALCULOS AUXILIARES'!D3 -> 46175 | E4: ='CALCULOS AUXILIARES'!E3 -> 46206 | F4: ='CALCULOS AUXILIARES'!F3 -> 46237 | G4: ='CALCULOS AUXILIARES'!G3 -> 46268 | H4: ='CALCULOS AUXILIARES'!H3 -> 46299 | I4: ='CALCULOS AUXILIARES'!I3 -> 46330 | ... N4: ='CALCULOS AUXILIARES'!N3 -> 46485
A5: =INSTRUCCIONES!A2 -> Project Manager | B5: ='CALCULOS AUXILIARES'!B109 -> 4101.3441 | C5: ='CALCULOS AUXILIARES'!C109 -> 4394.2973 | D5: ='CALCULOS AUXILIARES'!D109 -> 4394.2973 | E5: ='CALCULOS AUXILIARES'!E109 -> 4394.2973 | F5: ='CALCULOS AUXILIARES'!F109 -> 4394.2973 | G5: ='CALCULOS AUXILIARES'!G109 -> 4394.2973 | H5: ='CALCULOS AUXILIARES'!H109 -> 4394.2973 | I5: ='CALCULOS AUXILIARES'!I109 -> 4394.2973 | ... N5: ='CALCULOS AUXILIARES'!N109 -> 4394.2973 | O5: =SUM(B5:N5) -> 56832.911
A6: =INSTRUCCIONES!A8 -> Arquitecto de Software | B6: ='CALCULOS AUXILIARES'!B110 -> 3859.9416 | C6: ='CALCULOS AUXILIARES'!C110 -> 4135.6517 | D6: ='CALCULOS AUXILIARES'!D110 -> 4135.6517 | E6: ='CALCULOS AUXILIARES'!E110 -> 4135.6517 | F6: ='CALCULOS AUXILIARES'!F110 -> 4135.6517 | G6: ='CALCULOS AUXILIARES'!G110 -> 4135.6517 | H6: ='CALCULOS AUXILIARES'!H110 -> 4135.6517 | I6: ='CALCULOS AUXILIARES'!I110 -> 4135.6517 | ... N6: ='CALCULOS AUXILIARES'!N110 -> 4135.6517 | O6: =SUM(B6:N6) -> 53487.762
A7: =INSTRUCCIONES!A9 -> DevOps | B7: ='CALCULOS AUXILIARES'!B111 -> 3766.1804 | C7: ='CALCULOS AUXILIARES'!C111 -> 4035.1933 | D7: ='CALCULOS AUXILIARES'!D111 -> 4035.1933 | E7: ='CALCULOS AUXILIARES'!E111 -> 4035.1933 | F7: ='CALCULOS AUXILIARES'!F111 -> 4035.1933 | G7: ='CALCULOS AUXILIARES'!G111 -> 4035.1933 | H7: ='CALCULOS AUXILIARES'!H111 -> 4035.1933 | I7: ='CALCULOS AUXILIARES'!I111 -> 4035.1933 | ... N7: ='CALCULOS AUXILIARES'!N111 -> 4035.1933 | O7: =SUM(B7:N7) -> 52188.5
A8: =INSTRUCCIONES!A10 -> Responsable de Seguridad | B8: ='CALCULOS AUXILIARES'!B112 -> 3944.3493 | C8: ='CALCULOS AUXILIARES'!C112 -> 4226.0885 | D8: ='CALCULOS AUXILIARES'!D112 -> 4226.0885 | E8: ='CALCULOS AUXILIARES'!E112 -> 4226.0885 | F8: ='CALCULOS AUXILIARES'!F112 -> 4226.0885 | G8: ='CALCULOS AUXILIARES'!G112 -> 4226.0885 | H8: ='CALCULOS AUXILIARES'!H112 -> 4226.0885 | I8: ='CALCULOS AUXILIARES'!I112 -> 4226.0885 | ... N8: ='CALCULOS AUXILIARES'!N112 -> 4226.0885 | O8: =SUM(B8:N8) -> 54657.411
A9: =INSTRUCCIONES!A11 -> Arquitecto de Base de Datos | B9: ='CALCULOS AUXILIARES'!B113 -> 3926.9214 | C9: ='CALCULOS AUXILIARES'!C113 -> 4207.4158 | D9: ='CALCULOS AUXILIARES'!D113 -> 4207.4158 | E9: ='CALCULOS AUXILIARES'!E113 -> 4207.4158 | F9: ='CALCULOS AUXILIARES'!F113 -> 4207.4158 | G9: ='CALCULOS AUXILIARES'!G113 -> 4207.4158 | H9: ='CALCULOS AUXILIARES'!H113 -> 4207.4158 | I9: ='CALCULOS AUXILIARES'!I113 -> 4207.4158 | ... N9: ='CALCULOS AUXILIARES'!N113 -> 4207.4158 | O9: =SUM(B9:N9) -> 54415.911
A10: =INSTRUCCIONES!A12 -> Desarrollador Backend | B10: ='CALCULOS AUXILIARES'!B114 -> 3926.9936 | C10: ='CALCULOS AUXILIARES'!C114 -> 4207.4932 | D10: ='CALCULOS AUXILIARES'!D114 -> 4207.4932 | E10: ='CALCULOS AUXILIARES'!E114 -> 4207.4932 | F10: ='CALCULOS AUXILIARES'!F114 -> 4207.4932 | G10: ='CALCULOS AUXILIARES'!G114 -> 4207.4932 | H10: ='CALCULOS AUXILIARES'!H114 -> 4207.4932 | I10: ='CALCULOS AUXILIARES'!I114 -> 4207.4932 | ... N10: ='CALCULOS AUXILIARES'!N114 -> 4207.4932 | O10: =SUM(B10:N10) -> 54416.911
A11: =INSTRUCCIONES!A13 -> Desarrollador Frontend | B11: ='CALCULOS AUXILIARES'!B115 -> 3927.0658 | C11: ='CALCULOS AUXILIARES'!C115 -> 4207.5705 | D11: ='CALCULOS AUXILIARES'!D115 -> 4207.5705 | E11: ='CALCULOS AUXILIARES'!E115 -> 4207.5705 | F11: ='CALCULOS AUXILIARES'!F115 -> 4207.5705 | G11: ='CALCULOS AUXILIARES'!G115 -> 4207.5705 | H11: ='CALCULOS AUXILIARES'!H115 -> 4207.5705 | I11: ='CALCULOS AUXILIARES'!I115 -> 4207.5705 | ... N11: ='CALCULOS AUXILIARES'!N115 -> 4207.5705 | O11: =SUM(B11:N11) -> 54417.911
A12: =INSTRUCCIONES!A14 -> QA Consultant | B12: ='CALCULOS AUXILIARES'!B116 -> 8059.7531 | C12: ='CALCULOS AUXILIARES'!C116 -> 8635.4498 | D12: ='CALCULOS AUXILIARES'!D116 -> 8635.4498 | E12: ='CALCULOS AUXILIARES'!E116 -> 8635.4498 | F12: ='CALCULOS AUXILIARES'!F116 -> 8635.4498 | G12: ='CALCULOS AUXILIARES'!G116 -> 8635.4498 | H12: ='CALCULOS AUXILIARES'!H116 -> 8635.4498 | I12: ='CALCULOS AUXILIARES'!I116 -> 8635.4498 | ... N12: ='CALCULOS AUXILIARES'!N116 -> 8635.4498 | O12: =SUM(B12:N12) -> 111685.15
A13: =INSTRUCCIONES!A15 -> Soporte | B13: ='CALCULOS AUXILIARES'!B117 -> 3609.1134 | C13: ='CALCULOS AUXILIARES'!C117 -> 3866.9072 | D13: ='CALCULOS AUXILIARES'!D117 -> 3866.9072 | E13: ='CALCULOS AUXILIARES'!E117 -> 3866.9072 | F13: ='CALCULOS AUXILIARES'!F117 -> 3866.9072 | G13: ='CALCULOS AUXILIARES'!G117 -> 3866.9072 | H13: ='CALCULOS AUXILIARES'!H117 -> 3866.9072 | I13: ='CALCULOS AUXILIARES'!I117 -> 3866.9072 | ... N13: ='CALCULOS AUXILIARES'!N117 -> 3866.9072 | O13: =SUM(B13:N13) -> 50012
A14: =INSTRUCCIONES!#REF! -> #REF! | B14: ='CALCULOS AUXILIARES'!B118 -> 39121.663 | C14: ='CALCULOS AUXILIARES'!C118 -> 41916.067 | D14: ='CALCULOS AUXILIARES'!D118 -> 41916.067 | E14: ='CALCULOS AUXILIARES'!E118 -> 41916.067 | F14: ='CALCULOS AUXILIARES'!F118 -> 41916.067 | G14: ='CALCULOS AUXILIARES'!G118 -> 41916.067 | H14: ='CALCULOS AUXILIARES'!H118 -> 41916.067 | I14: ='CALCULOS AUXILIARES'!I118 -> 41916.067 | ... N14: ='CALCULOS AUXILIARES'!N118 -> 41916.067 | O14: =SUM(B14:N14) -> 542114.47
A15: Totales Flujo de Fondos | B15: =SUM(B5:B14) -> 78243.325 | C15: =SUM(C5:C14) -> 83832.134 | D15: =SUM(D5:D14) -> 83832.134 | E15: =SUM(E5:E14) -> 83832.134 | F15: =SUM(F5:F14) -> 83832.134 | G15: =SUM(G5:G14) -> 83832.134 | H15: =SUM(H5:H14) -> 83832.134 | I15: =SUM(I5:I14) -> 83832.134 | ... O15: =SUM(O5:O14) -> 1084228.9
A17: Costo total del Proyecto | B17: =$O$15 -> 1084228.9
A18: Promedio Costo Mensual | B18: =AVERAGE(B15:N15) -> 83402.226

Sheet Estimación de Costos Avanzada (
A1: Estimación de Costos . Calculo de TCO. P&L (Profit & Loss, perdidas y ganancias) Pricing Cloud AWS: https://calculator.s3.amazonaws.com/index.html Princing Cloud Azure: https://azure.microsoft.com/en-us/pricing/calculator/ Pricing Cloud https://cloud.google.com/products/calculator/ Pricing PaaS Heroku: https://www.heroku.com/pricing
A2: ID | B2: Categoría | D2: Concepto | E2: ='Estimación de Costos Básica HR '!B4 -> 46113 | F2: ='Estimación de Costos Básica HR '!C4 -> 46144 | G2: ='Estimación de Costos Básica HR '!D4 -> 46175 | H2: ='Estimación de Costos Básica HR '!E4 -> 46206 | I2: ='Estimación de Costos Básica HR '!F4 -> 46237 | J2: ='Estimación de Costos Básica HR '!G4 -> 46268 | K2: ='Estimación de Costos Básica HR '!H4 -> 46299 | L2: ='Estimación de Costos Básica HR '!I4 -> 46330 | ... Q2: ='Estimación de Costos Básica HR '!N4 -> 46485 | R2: Costos Totales por categoría | S2: Consideraciones, y detalles de los costos incluidos en cada partida
B3: Oficinas | C3: Facilities | D3: Alquiler/Expensas | R3: =SUM(E3:Q3) -> 0
D4: Electricidad/Agua/Impuestos Varios | R4: =SUM(E4:Q4) -> 0
D5: Internet | F5: 12000 | G5: 12001 | H5: 12002 | I5: 12003 | J5: 12004 | K5: 12005 | L5: 12006 | M5: 12007 | N5: 12008 | O5: 12009 | P5: 12010 | Q5: 12011 | R5: =SUM(E5:Q5) -> 144066
D6: Equipos de oficina (laptops/tablets/Celulares/movilidad) | R6: =SUM(E6:Q6) -> 0
D7: Viaticos del equipo de trabajo | R7: =SUM(E7:Q7) -> 0
D8: Limpieza | R8: =SUM(E8:Q8) -> 0
D9: Otros/cafetera! | R9: =SUM(E9:Q9) -> 0
B10: Infraestructura | C10: Licencias de SW Base | D10: Compra Licencias de Sistema Operativo | R10: =SUM(E10:Q10) -> 0
D11: Costo Mensual de Licencias de Sistema Operativo | R11: =SUM(E11:Q11) -> 0
C12: Servicios Cloud/OnPrem | D12: Costo de Instancias / Servicios | E12: =70*140 -> 9800 | F12: =70*140 -> 9800 | G12: =70*140 -> 9800 | H12: =70*140 -> 9800 | I12: =70*140 -> 9800 | J12: =70*140 -> 9800 | K12: =70*140 -> 9800 | L12: =70*140 -> 9800 | ... Q12: =70*140 -> 9800 | R12: =SUM(E12:Q12) -> 127400
D13: Costo de Almacenamiento | R13: =SUM(E13:Q13) -> 0
D14: Otros componentes de infraestructura | R14: =SUM(E14:Q14) -> 0
D15: Costo de Monitoreo | R15: =SUM(E15:Q15) -> 0
D16: Tráfico Web | R16: =SUM(E16:Q16) -> 0
D17: Licenciamiento de Sistemas Operativos | R17: =SUM(E17:Q17) -> 0
D18: Sistemas/Almacenamiento de Backup | R18: =SUM(E18:Q18) -> 0
B19: Ingeniería de Software | C19: Herramientas de Integración | D19: Jenkins | R19: =SUM(E19:Q19) -> 0
R20: =SUM(E20:Q20) -> 0
C21: Herramientas de Testing | D21: Selenium | R21: =SUM(E21:Q21) -> 0
R22: =SUM(E22:Q22) -> 0
C23: Herramientas de Monitoreo | R23: =SUM(E23:Q23) -> 0
R24: =SUM(E24:Q24) -> 0
C25: Repositorios de Versionado | D25: Bitbucket 7 usuarios a USD 3 c/u | E25: =21*7*140 -> 20580 | F25: =21*7*140 -> 20580 | G25: =21*7*140 -> 20580 | H25: =21*7*140 -> 20580 | I25: =21*7*140 -> 20580 | J25: =21*7*140 -> 20580 | K25: =21*7*140 -> 20580 | L25: =21*7*140 -> 20580 | ... Q25: =21*7*140 -> 20580 | R25: =SUM(E25:Q25) -> 267540
R26: =SUM(E26:Q26) -> 0
C27: Compra de Herramientas Previas | R27: =SUM(E27:Q27) -> 0
C28: Otras Herramientas | R28: =SUM(E28:Q28) -> 0
B29: HR (considerar revisiones salariales a lo largo del año) | C29: Equipo de Dirección | D29: (Detallar cada miembro del equipo) | R29: =SUM(E29:Q29) -> 0
C30: Equipo de Infraestructura | D30: ... | R30: =SUM(E30:Q30) -> 0
C31: Equipo de Desarrollo | D31: ... | R31: =SUM(E31:Q31) -> 0
C32: Equipo de Administración/finanzas | D32: ... | R32: =SUM(E32:Q32) -> 0
C33: Equipo de marketing digital | D33: ... | R33: =SUM(E33:Q33) -> 0
C34: Equipo de comercial | D34: ... | R34: =SUM(E34:Q34) -> 0
B35: Comercial Marketing Digital | C35: Diseño | D35: Diseño de Marca / Logo / Poster | R35: =SUM(E35:Q35) -> 0
C36: Facebook | D36: Facebook Ads | R36: =SUM(E36:Q36) -> 0
C37: Instagram | D37: Instagram Ads | R37: =SUM(E37:Q37) -> 0
C38: Google | D38: Adwords | R38: =SUM(E38:Q38) -> 0
D39: Adsense | R39: =SUM(E39:Q39) -> 0
C40: Mailing | D40: Mailchimp/Sendgrid/... | R40: =SUM(E40:Q40) -> 0
C41: SMS | D41: Twilio/AWS SNS/... | R41: =SUM(E41:Q41) -> 0
B42: Otros | C42: Otros conceptos variables | R42: =SUM(E42:Q42) -> 0
R43: =SUM(E43:Q43) -> 0
C44: Otros conceptos fijos | R44: =SUM(E44:Q44) -> 0
R45: =SUM(E45:Q45) -> 0
A46: Totales | E46: =SUM(E3:E45) -> 30380 | F46: =SUM(F3:F45) -> 42380 | G46: =SUM(G3:G45) -> 42381 | H46: =SUM(H3:H45) -> 42382 | I46: =SUM(I3:I45) -> 42383 | J46: =SUM(J3:J45) -> 42384 | K46: =SUM(K3:K45) -> 42385 | L46: =SUM(L3:L45) -> 42386 | ... R46: =SUM(R3:R45) -> 539006
D48: TOTAL USD | E48: =E46/E49 -> 273.32434 | F48: =F46/F49 -> 379.06977 | G48: =G46/G49 -> 379.07871 | H48: =H46/H49 -> 379.08766 | I48: =I46/I49 -> 379.0966 | J48: =J46/J49 -> 379.10555 | K48: =K46/K49 -> 379.11449 | L48: =L46/L49 -> 379.12343 | ... Q48: =Q46/Q49 -> 379.16816 | R48: =SUM(E48:Q48) -> 4822.7519
D49: Cotizacion de moneda extranjera (USD) proyectada | E49: =85.5*1.3 -> 111.15 | F49: =86*1.3 -> 111.8 | G49: =86*1.3 -> 111.8 | H49: =86*1.3 -> 111.8 | I49: =86*1.3 -> 111.8 | J49: =86*1.3 -> 111.8 | K49: =86*1.3 -> 111.8 | L49: =86*1.3 -> 111.8 | M49: =86*1.3 -> 111.8 | ... Q49: =86*1.3 -> 111.8
